[
  {
    "id": "mono-1",
    "brand": "Babolat",
    "name": "RPM Blast",
    "type": "Polyester",
    "power": 6,
    "control": 9,
    "spin": 10,
    "comfort": 5,
    "durability": 8,
    "tension_min": 22,
    "tension_max": 26,
    "price": 27,
    "player_profile": "Lifteur puissant, joueur de fond"
  },
  {
    "id": "mono-2",
    "brand": "Babolat",
    "name": "RPM Rough",
    "type": "Polyester",
    "power": 6,
    "control": 8,
    "spin": 10,
    "comfort": 5,
    "durability": 8,
    "tension_min": 22,
    "tension_max": 26,
    "price": 27,
    "player_profile": "Joueur lifté cherchant du grip"
  },
  {
    "id": "mono-3",
    "brand": "Babolat",
    "name": "RPM Soft",
    "type": "Polyester",
    "power": 7,
    "control": 7,
    "spin": 8,
    "comfort": 7,
    "durability": 7,
    "tension_min": 21,
    "tension_max": 25,
    "price": 27,
    "player_profile": "Joueur polyvalent, bras sensible"
  },
  {
    "id": "mono-4",
    "brand": "Babolat",
    "name": "Xcel",
    "type": "Multifilament",
    "power": 9,
    "control": 6,
    "spin": 5,
    "comfort": 10,
    "durability": 5,
    "tension_min": 23,
    "tension_max": 27,
    "price": 22,
    "player_profile": "Joueur loisir ou sensible"
  },
  {
    "id": "mono-5",
    "brand": "Babolat",
    "name": "Addiction",
    "type": "Multifilament",
    "power": 8,
    "control": 6,
    "spin": 5,
    "comfort": 8,
    "durability": 6,
    "tension_min": 23,
    "tension_max": 27,
    "price": 22,
    "player_profile": "Joueur régulier intermédiaire"
  },
  {
    "id": "mono-6",
    "brand": "Babolat",
    "name": "VS Touch",
    "type": "Boyau naturel",
    "power": 10,
    "control": 8,
    "spin": 8,
    "comfort": 10,
    "durability": 7,
    "tension_min": 23,
    "tension_max": 28,
    "price": 40,
    "player_profile": "Joueur exigeant ou hybride haut de gamme"
  },
  {
    "id": "mono-7",
    "brand": "Wilson",
    "name": "Luxilon ALU Power",
    "type": "Polyester",
    "power": 6,
    "control": 9,
    "spin": 9,
    "comfort": 5,
    "durability": 9,
    "tension_min": 22,
    "tension_max": 26,
    "price": 28,
    "player_profile": "Joueur agressif, lifteur"
  },
  {
    "id": "mono-8",
    "brand": "Wilson",
    "name": "Luxilon Element",
    "type": "Polyester",
    "power": 7,
    "control": 8,
    "spin": 8,
    "comfort": 7,
    "durability": 8,
    "tension_min": 22,
    "tension_max": 26,
    "price": 25,
    "player_profile": "Joueur contrôle cherchant confort"
  },
  {
    "id": "mono-9",
    "brand": "Wilson",
    "name": "Revolve",
    "type": "Polyester",
    "power": 7,
    "control": 8,
    "spin": 9,
    "comfort": 6,
    "durability": 7,
    "tension_min": 22,
    "tension_max": 26,
    "price": 22,
    "player_profile": "Joueur moderne polyvalent"
  },
  {
    "id": "mono-10",
    "brand": "Wilson",
    "name": "NXT",
    "type": "Multifilament",
    "power": 9,
    "control": 6,
    "spin": 5,
    "comfort": 9,
    "durability": 6,
    "tension_min": 24,
    "tension_max": 28,
    "price": 22,
    "player_profile": "Joueur loisir / bras sensible"
  },
  {
    "id": "mono-11",
    "brand": "Wilson",
    "name": "Sensation",
    "type": "Multifilament",
    "power": 8,
    "control": 5,
    "spin": 4,
    "comfort": 8,
    "durability": 5,
    "tension_min": 23,
    "tension_max": 27,
    "price": 18,
    "player_profile": "Débutant ou joueur occasionnel"
  },
  {
    "id": "mono-12",
    "brand": "Wilson",
    "name": "Natural Gut",
    "type": "Boyau naturel",
    "power": 10,
    "control": 8,
    "spin": 8,
    "comfort": 10,
    "durability": 7,
    "tension_min": 23,
    "tension_max": 28,
    "price": 40,
    "player_profile": "Joueur axé toucher et confort"
  },
  {
    "id": "mono-13",
    "brand": "Head",
    "name": "Lynx",
    "type": "Polyester",
    "power": 7,
    "control": 8,
    "spin": 8,
    "comfort": 6,
    "durability": 7,
    "tension_min": 22,
    "tension_max": 26,
    "price": 18,
    "player_profile": "Joueur polyvalent"
  },
  {
    "id": "mono-14",
    "brand": "Head",
    "name": "Lynx Tour",
    "type": "Polyester",
    "power": 6,
    "control": 9,
    "spin": 9,
    "comfort": 5,
    "durability": 8,
    "tension_min": 22,
    "tension_max": 26,
    "price": 20,
    "player_profile": "Lifteur recherchant précision"
  },
  {
    "id": "mono-15",
    "brand": "Head",
    "name": "Hawk / Hawk Touch",
    "type": "Polyester",
    "power": 6,
    "control": 9,
    "spin": 8,
    "comfort": 5,
    "durability": 9,
    "tension_min": 22,
    "tension_max": 26,
    "price": 20,
    "player_profile": "Joueur puissant / compétiteur"
  },
  {
    "id": "mono-16",
    "brand": "Head",
    "name": "Velocity MLT",
    "type": "Multifilament",
    "power": 8,
    "control": 7,
    "spin": 6,
    "comfort": 9,
    "durability": 6,
    "tension_min": 23,
    "tension_max": 27,
    "price": 20,
    "player_profile": "Joueur loisir ou intermédiaire"
  },
  {
    "id": "mono-17",
    "brand": "Head",
    "name": "Reflex MLT",
    "type": "Multifilament",
    "power": 9,
    "control": 6,
    "spin": 5,
    "comfort": 10,
    "durability": 5,
    "tension_min": 24,
    "tension_max": 28,
    "price": 22,
    "player_profile": "Joueur cherchant douceur et toucher"
  },
  {
    "id": "mono-18",
    "brand": "Head",
    "name": "RIP Control",
    "type": "Multifilament (ruban)",
    "power": 7,
    "control": 9,
    "spin": 6,
    "comfort": 8,
    "durability": 9,
    "tension_min": 23,
    "tension_max": 27,
    "price": 20,
    "player_profile": "Joueur contrôle, bras sensible, recherche longévité"
  },
  {
    "id": "mono-19",
    "brand": "Tecnifibre",
    "name": "Razor Code / Razor Soft",
    "type": "Polyester",
    "power": 7,
    "control": 9,
    "spin": 8,
    "comfort": 6,
    "durability": 8,
    "tension_min": 22,
    "tension_max": 26,
    "price": 23,
    "player_profile": "Joueur compétiteur"
  },
  {
    "id": "mono-20",
    "brand": "Tecnifibre",
    "name": "Ice Code",
    "type": "Polyester",
    "power": 8,
    "control": 8,
    "spin": 8,
    "comfort": 6,
    "durability": 8,
    "tension_min": 22,
    "tension_max": 26,
    "price": 23,
    "player_profile": "Joueur polyvalent"
  },
  {
    "id": "mono-21",
    "brand": "Tecnifibre",
    "name": "Black Code",
    "type": "Polyester",
    "power": 7,
    "control": 8,
    "spin": 9,
    "comfort": 6,
    "durability": 8,
    "tension_min": 22,
    "tension_max": 26,
    "price": 24,
    "player_profile": "Joueur lifté cherchant spin et souplesse"
  },
  {
    "id": "mono-22",
    "brand": "Tecnifibre",
    "name": "X-One Biphase",
    "type": "Multifilament",
    "power": 10,
    "control": 7,
    "spin": 6,
    "comfort": 10,
    "durability": 5,
    "tension_min": 24,
    "tension_max": 28,
    "price": 28,
    "player_profile": "Joueur sensible / polyvalent"
  },
  {
    "id": "mono-23",
    "brand": "Tecnifibre",
    "name": "NRG²",
    "type": "Multifilament",
    "power": 9,
    "control": 6,
    "spin": 6,
    "comfort": 9,
    "durability": 5,
    "tension_min": 24,
    "tension_max": 28,
    "price": 25,
    "player_profile": "Joueur loisir à fort lift"
  },
  {
    "id": "mono-24",
    "brand": "Tecnifibre",
    "name": "HDMX",
    "type": "Multifilament hybride",
    "power": 8,
    "control": 7,
    "spin": 7,
    "comfort": 8,
    "durability": 6,
    "tension_min": 23,
    "tension_max": 26,
    "price": 21,
    "player_profile": "Joueur recherchant équilibre global"
  },
  {
    "id": "mono-25",
    "brand": "Luxilon",
    "name": "ALU Power / Rough",
    "type": "Polyester",
    "power": 6,
    "control": 9,
    "spin": 9,
    "comfort": 5,
    "durability": 9,
    "tension_min": 22,
    "tension_max": 26,
    "price": 28,
    "player_profile": "Joueur agressif"
  },
  {
    "id": "mono-26",
    "brand": "Luxilon",
    "name": "4G / 4G Soft",
    "type": "Polyester",
    "power": 6,
    "control": 9,
    "spin": 8,
    "comfort": 5,
    "durability": 10,
    "tension_min": 22,
    "tension_max": 26,
    "price": 28,
    "player_profile": "Joueur puissance/contrôle"
  },
  {
    "id": "mono-27",
    "brand": "Luxilon",
    "name": "Element / Smart",
    "type": "Polyester",
    "power": 7,
    "control": 8,
    "spin": 8,
    "comfort": 7,
    "durability": 8,
    "tension_min": 22,
    "tension_max": 26,
    "price": 25,
    "player_profile": "Joueur polyvalent"
  },
  {
    "id": "mono-28",
    "brand": "Yonex",
    "name": "Poly Tour Pro",
    "type": "Polyester",
    "power": 7,
    "control": 8,
    "spin": 8,
    "comfort": 6,
    "durability": 8,
    "tension_min": 22,
    "tension_max": 26,
    "price": 20,
    "player_profile": "Joueur régulier"
  },
  {
    "id": "mono-29",
    "brand": "Yonex",
    "name": "Poly Tour Rev",
    "type": "Polyester",
    "power": 6,
    "control": 8,
    "spin": 10,
    "comfort": 5,
    "durability": 8,
    "tension_min": 22,
    "tension_max": 26,
    "price": 20,
    "player_profile": "Lifteur"
  },
  {
    "id": "mono-30",
    "brand": "Yonex",
    "name": "Poly Tour Fire",
    "type": "Polyester",
    "power": 8,
    "control": 8,
    "spin": 8,
    "comfort": 5,
    "durability": 8,
    "tension_min": 22,
    "tension_max": 26,
    "price": 20,
    "player_profile": "Joueur offensif"
  },
  {
    "id": "mono-31",
    "brand": "Yonex",
    "name": "Poly Tour Air",
    "type": "Polyester",
    "power": 8,
    "control": 7,
    "spin": 7,
    "comfort": 8,
    "durability": 7,
    "tension_min": 23,
    "tension_max": 27,
    "price": 22,
    "player_profile": "Joueur sensible ou junior"
  },
  {
    "id": "mono-32",
    "brand": "Yonex",
    "name": "Rexis Comfort / Speed",
    "type": "Multifilament",
    "power": 9,
    "control": 7,
    "spin": 6,
    "comfort": 9,
    "durability": 6,
    "tension_min": 24,
    "tension_max": 28,
    "price": 22,
    "player_profile": "Joueur confort"
  },
  {
    "id": "mono-33",
    "brand": "Solinco",
    "name": "Hyper-G",
    "type": "Polyester",
    "power": 6,
    "control": 9,
    "spin": 10,
    "comfort": 5,
    "durability": 8,
    "tension_min": 22,
    "tension_max": 26,
    "price": 23,
    "player_profile": "Lifteur"
  },
  {
    "id": "mono-34",
    "brand": "Solinco",
    "name": "Hyper-G Soft",
    "type": "Polyester",
    "power": 7,
    "control": 8,
    "spin": 9,
    "comfort": 7,
    "durability": 7,
    "tension_min": 22,
    "tension_max": 26,
    "price": 23,
    "player_profile": "Joueur polyvalent"
  },
  {
    "id": "mono-35",
    "brand": "Solinco",
    "name": "Confidential",
    "type": "Polyester",
    "power": 6,
    "control": 10,
    "spin": 8,
    "comfort": 5,
    "durability": 9,
    "tension_min": 22,
    "tension_max": 26,
    "price": 25,
    "player_profile": "Frappeur à plat / contrôle"
  },
  {
    "id": "mono-36",
    "brand": "Solinco",
    "name": "Tour Bite",
    "type": "Polyester",
    "power": 6,
    "control": 9,
    "spin": 10,
    "comfort": 5,
    "durability": 8,
    "tension_min": 22,
    "tension_max": 26,
    "price": 23,
    "player_profile": "Joueur lifté/agressif"
  },
  {
    "id": "mono-37",
    "brand": "Signum Pro",
    "name": "Poly Plasma",
    "type": "Polyester",
    "power": 6,
    "control": 9,
    "spin": 7,
    "comfort": 6,
    "durability": 9,
    "tension_min": 22,
    "tension_max": 26,
    "price": 20,
    "player_profile": "Joueur régulier"
  },
  {
    "id": "mono-38",
    "brand": "Signum Pro",
    "name": "Tornado",
    "type": "Polyester",
    "power": 7,
    "control": 8,
    "spin": 9,
    "comfort": 6,
    "durability": 8,
    "tension_min": 22,
    "tension_max": 26,
    "price": 20,
    "player_profile": "Joueur lifteur"
  },
  {
    "id": "mono-39",
    "brand": "Signum Pro",
    "name": "Firestorm",
    "type": "Polyester",
    "power": 8,
    "control": 8,
    "spin": 8,
    "comfort": 6,
    "durability": 8,
    "tension_min": 22,
    "tension_max": 26,
    "price": 20,
    "player_profile": "Joueur polyvalent"
  },
  {
    "id": "mono-40",
    "brand": "Signum Pro",
    "name": "Micronite",
    "type": "Multifilament",
    "power": 9,
    "control": 6,
    "spin": 5,
    "comfort": 9,
    "durability": 6,
    "tension_min": 24,
    "tension_max": 28,
    "price": 20,
    "player_profile": "Joueur sensible"
  },
  {
    "id": "mono-41",
    "brand": "Kirschbaum",
    "name": "Pro Line II",
    "type": "Polyester",
    "power": 7,
    "control": 8,
    "spin": 8,
    "comfort": 6,
    "durability": 8,
    "tension_min": 22,
    "tension_max": 26,
    "price": 20,
    "player_profile": "Joueur compétiteur"
  },
  {
    "id": "mono-42",
    "brand": "Kirschbaum",
    "name": "Max Power",
    "type": "Polyester",
    "power": 6,
    "control": 9,
    "spin": 8,
    "comfort": 5,
    "durability": 9,
    "tension_min": 22,
    "tension_max": 26,
    "price": 20,
    "player_profile": "Frappeur fort"
  },
  {
    "id": "mono-43",
    "brand": "Kirschbaum",
    "name": "Spiky Shark",
    "type": "Polyester",
    "power": 7,
    "control": 8,
    "spin": 9,
    "comfort": 5,
    "durability": 8,
    "tension_min": 22,
    "tension_max": 26,
    "price": 20,
    "player_profile": "Joueur lifteur"
  },
  {
    "id": "mono-44",
    "brand": "Kirschbaum",
    "name": "Touch Multifiber",
    "type": "Multifilament",
    "power": 9,
    "control": 6,
    "spin": 5,
    "comfort": 9,
    "durability": 6,
    "tension_min": 24,
    "tension_max": 28,
    "price": 20,
    "player_profile": "Joueur loisir"
  },
  {
    "id": "mono-45",
    "brand": "MSV",
    "name": "Focus Hex",
    "type": "Polyester",
    "power": 7,
    "control": 8,
    "spin": 9,
    "comfort": 5,
    "durability": 8,
    "tension_min": 22,
    "tension_max": 26,
    "price": 20,
    "player_profile": "Lifteur"
  },
  {
    "id": "mono-46",
    "brand": "MSV",
    "name": "Co-Focus",
    "type": "Polyester",
    "power": 7,
    "control": 9,
    "spin": 8,
    "comfort": 6,
    "durability": 8,
    "tension_min": 22,
    "tension_max": 26,
    "price": 20,
    "player_profile": "Joueur contrôle"
  },
  {
    "id": "mono-47",
    "brand": "MSV",
    "name": "Swift",
    "type": "Polyester",
    "power": 8,
    "control": 7,
    "spin": 7,
    "comfort": 7,
    "durability": 7,
    "tension_min": 23,
    "tension_max": 27,
    "price": 20,
    "player_profile": "Joueur loisir/transition"
  },
  {
    "id": "mono-48",
    "brand": "Prince",
    "name": "Warrior Response",
    "type": "Polyester",
    "power": 7,
    "control": 8,
    "spin": 8,
    "comfort": 6,
    "durability": 8,
    "tension_min": 22,
    "tension_max": 26,
    "price": 20,
    "player_profile": "Joueur polyvalent"
  },
  {
    "id": "mono-49",
    "brand": "Prince",
    "name": "Premier Touch",
    "type": "Multifilament",
    "power": 9,
    "control": 6,
    "spin": 5,
    "comfort": 10,
    "durability": 5,
    "tension_min": 24,
    "tension_max": 28,
    "price": 20,
    "player_profile": "Joueur sensible"
  },
  {
    "id": "mono-50",
    "brand": "Weiss Cannon",
    "name": "Silverstring",
    "type": "Polyester",
    "power": 7,
    "control": 9,
    "spin": 8,
    "comfort": 6,
    "durability": 8,
    "tension_min": 22,
    "tension_max": 26,
    "price": 20,
    "player_profile": "Joueur compétiteur"
  },
  {
    "id": "mono-51",
    "brand": "Weiss Cannon",
    "name": "Ultra Cable",
    "type": "Polyester",
    "power": 6,
    "control": 9,
    "spin": 10,
    "comfort": 4,
    "durability": 9,
    "tension_min": 22,
    "tension_max": 26,
    "price": 20,
    "player_profile": "Gros lifteur"
  },
  {
    "id": "mono-52",
    "brand": "Gosen",
    "name": "AK Pro CX",
    "type": "Multifilament",
    "power": 8,
    "control": 7,
    "spin": 6,
    "comfort": 9,
    "durability": 7,
    "tension_min": 24,
    "tension_max": 28,
    "price": 20,
    "player_profile": "Joueur confort/toucher"
  },
  {
    "id": "mono-53",
    "brand": "Diadem",
    "name": "Solstice Power",
    "type": "Polyester",
    "power": 7,
    "control": 8,
    "spin": 10,
    "comfort": 6,
    "durability": 8,
    "tension_min": 22,
    "tension_max": 26,
    "price": 20,
    "player_profile": "Joueur lifté"
  },
  {
    "id": "mono-54",
    "brand": "Diadem",
    "name": "Evolution",
    "type": "Multifilament",
    "power": 9,
    "control": 7,
    "spin": 6,
    "comfort": 9,
    "durability": 6,
    "tension_min": 24,
    "tension_max": 28,
    "price": 20,
    "player_profile": "Joueur loisir"
  },
  {
    "id": "mono-55",
    "brand": "Tier One",
    "name": "Firewire / Ghost Wire",
    "type": "Polyester",
    "power": 7,
    "control": 8,
    "spin": 9,
    "comfort": 6,
    "durability": 8,
    "tension_min": 22,
    "tension_max": 26,
    "price": 20,
    "player_profile": "Joueur moderne"
  },
  {
    "id": "mono-56",
    "brand": "Toroline",
    "name": "Caviar / Wasabi / Whiteout",
    "type": "Polyester",
    "power": 7,
    "control": 9,
    "spin": 9,
    "comfort": 6,
    "durability": 8,
    "tension_min": 22,
    "tension_max": 26,
    "price": 20,
    "player_profile": "Joueur agressif"
  },
  {
    "id": "mono-57",
    "brand": "Artengo",
    "name": "TA 990 Spin",
    "type": "Polyester",
    "power": 7,
    "control": 8,
    "spin": 9,
    "comfort": 6,
    "durability": 8,
    "tension_min": 22,
    "tension_max": 26,
    "price": 17,
    "player_profile": "Lifteur moderne, joueur agressif"
  },
  {
    "id": "mono-58",
    "brand": "Artengo",
    "name": "TA 990 Power",
    "type": "Polyester",
    "power": 8,
    "control": 7,
    "spin": 8,
    "comfort": 6,
    "durability": 7,
    "tension_min": 22,
    "tension_max": 26,
    "price": 17,
    "player_profile": "Joueur offensif"
  },
  {
    "id": "mono-59",
    "brand": "Artengo",
    "name": "TA 960 Control",
    "type": "Polyester",
    "power": 6,
    "control": 9,
    "spin": 8,
    "comfort": 6,
    "durability": 9,
    "tension_min": 22,
    "tension_max": 26,
    "price": 17,
    "player_profile": "Joueur de précision"
  },
  {
    "id": "mono-60",
    "brand": "Artengo",
    "name": "TA 960 Comfort",
    "type": "Polyester",
    "power": 8,
    "control": 7,
    "spin": 7,
    "comfort": 8,
    "durability": 7,
    "tension_min": 22,
    "tension_max": 26,
    "price": 17,
    "player_profile": "Joueur intermédiaire, bras sensible"
  },
  {
    "id": "mono-61",
    "brand": "Artengo",
    "name": "TA 500 / TA 530",
    "type": "Multifilament",
    "power": 8,
    "control": 6,
    "spin": 5,
    "comfort": 9,
    "durability": 6,
    "tension_min": 24,
    "tension_max": 28,
    "price": 15,
    "player_profile": "Joueur loisir, recherche de douceur"
  },
  {
    "id": "mono-62",
    "brand": "Artengo",
    "name": "TA 100",
    "type": "Synthétique",
    "power": 9,
    "control": 5,
    "spin": 4,
    "comfort": 9,
    "durability": 5,
    "tension_min": 24,
    "tension_max": 28,
    "price": 12,
    "player_profile": "Débutant ou junior"
  }
]